Workbook

Sheet Cover
B2: YO-DEE YOGURT
B3: Sales & Financial Report
B5: Branch | C5: SAT Market — ตลาดนัด กกท
B6: Period | C6: June 2026
B7: Prepared | C7: 2026-06-07
B8: Currency | C8: Thai Baht (฿)
B10: SUMMARY — THIS PERIOD
B11: Total Revenue | C11: =IncomeStatement!B8 -> 246510
B12: Gross Profit | C12: =IncomeStatement!B13 -> 146701.8
B13: Operating Expenses | C13: =IncomeStatement!B20 -> 32800
B14: Net Profit | C14: =IncomeStatement!B21 -> 113901.8
B15: Net Margin | C15: =IncomeStatement!C21 -> 0.46205752
B16: Cups Sold | C16: =Sales!G26 -> 4650
B18: CONTENTS
B19: Assumptions | C19: Editable inputs — change these to model your month
B20: Sales | C20: Redesigned sales report by menu item (qty, price, revenue, mix)
B21: IncomeStatement | C21: Profit & Loss — revenue, COGS, gross profit, opex, net
B22: Journal | C22: Double-entry journal entries (sales, COGS, expenses)
B23: Variance | C23: Actual vs Budget with favourable/unfavourable flags
B26: Blue = input · Black = formula · Green = links from another sheet

Sheet Assumptions
A1: Assumptions & Inputs
A2: Blue cells are editable — every other sheet recalculates from these.
A4: Operating
A5: Days open in period | B5: 30 | C5: number of selling days
A6: PromptPay share of sales | B6: 0.55 | C6: rest collected as cash
A7: Cash share of sales | B7: =1-B6 -> 0.45 | C7: = 1 − PromptPay share
A8: Cost of goods
A9: Ingredient cost (% of revenue) | B9: 0.32 | C9: yogurt, fruit, toppings
A10: Packaging cost per cup (฿) | B10: 4.5 | C10: cup + lid + spoon + bag
A11: Topping add-ons
A12: Avg topping add-ons per day | B12: 60 | C12: extra toppings customers add
A13: Topping price (฿) | B13: 10 | C13: per add-on
A14: Operating expenses (per period, ฿)
A15: Rent / stall fee | B15: 8000
A16: Staff wages | B16: 18000
A17: Utilities (electric / water / gas) | B17: 3500
A18: Supplies & misc | B18: 2500
A19: Marketing / LINE | B19: 800
A20: Total operating expenses | B20: =SUM(B15:B19) -> 32800

Sheet Sales
A1: Sales Report — by menu item
A2: ="Period: "&Cover!C6 -> Period: June 2026
A4: No | B4: Menu (ไทย) | C4: Menu (English) | D4: Unit ฿ | E4: Avg/Day | F4: Days | G4: Units | H4: Gross ฿ | I4: % Sales
A5: 1 | B5: โยเกิร์ตปั่น Original | C5: Yogurt Original | D5: 40 | E5: 18 | F5: =Assumptions!$B$5 -> 30 | G5: =E5*F5 -> 540 | H5: =G5*D5 -> 21600 | I5: =H5/$H$25 -> 0.08762322
A6: 2 | B6: โยเกิร์ตปั่นข้าวเหนียวมูล | C6: Yogurt w/ Midnight Sticky Rice | D6: 49 | E6: 10 | F6: =Assumptions!$B$5 -> 30 | G6: =E6*F6 -> 300 | H6: =G6*D6 -> 14700 | I6: =H6/$H$25 -> 0.059632469
A7: 3 | B7: โยเกิร์ตปั่นข้าวโอ๊ต | C7: Yogurt with Oats | D7: 49 | E7: 8 | F7: =Assumptions!$B$5 -> 30 | G7: =E7*F7 -> 240 | H7: =G7*D7 -> 11760 | I7: =H7/$H$25 -> 0.047705975
A8: 4 | B8: โยเกิร์ตปั่นมะม่วง | C8: Yogurt with Mango | D8: 49 | E8: 16 | F8: =Assumptions!$B$5 -> 30 | G8: =E8*F8 -> 480 | H8: =G8*D8 -> 23520 | I8: =H8/$H$25 -> 0.095411951
A9: 5 | B9: โยเกิร์ตปั่นสตรอวเบอร์รี่ | C9: Yogurt with Strawberry | D9: 49 | E9: 14 | F9: =Assumptions!$B$5 -> 30 | G9: =E9*F9 -> 420 | H9: =G9*D9 -> 20580 | I9: =H9/$H$25 -> 0.083485457
A10: 6 | B10: โยเกิร์ตปั่นบัวลอย | C10: Yogurt with Rice Balls | D10: 49 | E10: 9 | F10: =Assumptions!$B$5 -> 30 | G10: =E10*F10 -> 270 | H10: =G10*D10 -> 13230 | I10: =H10/$H$25 -> 0.053669222
A11: 7 | B11: โยเกิร์ตปั่นบุกน้ำผึ้ง | C11: Yogurt with Honey Konjac | D11: 49 | E11: 7 | F11: =Assumptions!$B$5 -> 30 | G11: =E11*F11 -> 210 | H11: =G11*D11 -> 10290 | I11: =H11/$H$25 -> 0.041742728
A12: 8 | B12: โยเกิร์ตปั่นโอริโอ้ | C12: Yogurt with Oreo | D12: 49 | E12: 12 | F12: =Assumptions!$B$5 -> 30 | G12: =E12*F12 -> 360 | H12: =G12*D12 -> 17640 | I12: =H12/$H$25 -> 0.071558963
A13: 9 | B13: โยเกิร์ตปั่นคิทแคท | C13: Yogurt with KitKat | D13: 49 | E13: 11 | F13: =Assumptions!$B$5 -> 30 | G13: =E13*F13 -> 330 | H13: =G13*D13 -> 16170 | I13: =H13/$H$25 -> 0.065595716
A14: 10 | B14: โยเกิร์ตปั่นอโวคาโด | C14: Yogurt with Avocado | D14: 59 | E14: 6 | F14: =Assumptions!$B$5 -> 30 | G14: =E14*F14 -> 180 | H14: =G14*D14 -> 10620 | I14: =H14/$H$25 -> 0.043081417
A15: 11 | B15: โยเกิร์ตปั่นน้ำผึ้ง | C15: Yogurt with Honey | D15: 49 | E15: 7 | F15: =Assumptions!$B$5 -> 30 | G15: =E15*F15 -> 210 | H15: =G15*D15 -> 10290 | I15: =H15/$H$25 -> 0.041742728
A16: 12 | B16: โยเกิร์ตปั่นเฉาก๊วย | C16: Yogurt with Grass Jelly | D16: 49 | E16: 8 | F16: =Assumptions!$B$5 -> 30 | G16: =E16*F16 -> 240 | H16: =G16*D16 -> 11760 | I16: =H16/$H$25 -> 0.047705975
... A20: 16 | B20: โยเกิร์ตปั่นข้าวเหนียวมะม่วง | C20: Yogurt w/ Mango & Sticky Rice | D20: 59 | E20: 6 | F20: =Assumptions!$B$5 -> 30 | G20: =E20*F20 -> 180 | H20: =G20*D20 -> 10620 | I20: =H20/$H$25 -> 0.043081417
A21: + | B21: ท็อปปิ้งเพิ่ม (add-ons) | C21: Topping add-ons | D21: =Assumptions!$B$13 -> 10 | E21: =Assumptions!$B$12 -> 60 | F21: =Assumptions!$B$5 -> 30 | G21: =E21*F21 -> 1800 | H21: =G21*D21 -> 18000 | I21: =H21/$H$25 -> 0.07301935
C23: Total drink sales | H23: =SUM(H5:H20) -> 228510
C24: Topping add-on sales | H24: =H21 -> 18000
C25: TOTAL REVENUE | H25: =H23+H24 -> 246510
C26: Total cups sold | G26: =SUM(G5:G20) -> 4650
C27: Average ฿ / cup | H27: =H23/G26 -> 49.141935

Sheet IncomeStatement
A1: Income Statement (P&L)
A2: ="Period: "&Cover!C6 -> Period: June 2026
A4: Line | B4: Amount ฿ | C4: % Rev
A5: Revenue
A6: Drink sales | B6: =Sales!H23 -> 228510 | C6: =B6/$B$8 -> 0.92698065
A7: Topping add-ons | B7: =Sales!H24 -> 18000 | C7: =B7/$B$8 -> 0.07301935
A8: Total Revenue | B8: =B6+B7 -> 246510 | C8: =B8/$B$8 -> 1
A9: Cost of Goods Sold
A10: Ingredients | B10: =Assumptions!B9*B8 -> 78883.2 | C10: =B10/$B$8 -> 0.32
A11: Packaging | B11: =Assumptions!B10*Sales!G26 -> 20925 | C11: =B11/$B$8 -> 0.084884995
A12: Total COGS | B12: =B10+B11 -> 99808.2 | C12: =B12/$B$8 -> 0.40488499
A13: Gross Profit | B13: =B8-B12 -> 146701.8 | C13: =B13/$B$8 -> 0.59511501
A14: Operating Expenses
A15: Rent / stall fee | B15: =Assumptions!B15 -> 8000 | C15: =B15/$B$8 -> 0.032453045
A16: Staff wages | B16: =Assumptions!B16 -> 18000 | C16: =B16/$B$8 -> 0.07301935
A17: Utilities | B17: =Assumptions!B17 -> 3500 | C17: =B17/$B$8 -> 0.014198207
A18: Supplies & misc | B18: =Assumptions!B18 -> 2500 | C18: =B18/$B$8 -> 0.010141576
A19: Marketing / LINE | B19: =Assumptions!B19 -> 800 | C19: =B19/$B$8 -> 0.0032453045
A20: Total Operating Expenses | B20: =SUM(B15:B19) -> 32800 | C20: =B20/$B$8 -> 0.13305748
A21: NET PROFIT | B21: =B13-B20 -> 113901.8 | C21: =B21/$B$8 -> 0.46205752
A23: Note: cash-basis, single stall. No depreciation/tax modelled (turnover below the ฿1.8M VAT threshold).

Sheet Journal
A1: Journal Entries — period summary
A2: Double-entry. Total debits must equal total credits.
A4: 2026-06-30 | B4: JE-01 | C4: Cash on hand | D4: =IncomeStatement!B8*Assumptions!B7 -> 110929.5 | F4: Sales collected — cash
C5: PromptPay clearing | D5: =IncomeStatement!B8*Assumptions!B6 -> 135580.5 | F5: Sales collected — PromptPay
C6: Sales revenue — drinks | E6: =IncomeStatement!B6 -> 228510 | F6: Recognise drink sales
C7: Sales revenue — toppings | E7: =IncomeStatement!B7 -> 18000 | F7: Recognise topping sales
A8: 2026-06-30 | B8: JE-02 | C8: Cost of goods sold | D8: =IncomeStatement!B12 -> 99808.2 | F8: Recognise COGS for period
C9: Inventory — ingredients | E9: =IncomeStatement!B10 -> 78883.2 | F9: Yogurt, fruit, toppings used
C10: Packaging supplies | E10: =IncomeStatement!B11 -> 20925 | F10: Cups, lids, spoons, bags
A11: 2026-06-30 | B11: JE-03 | C11: Rent expense | D11: =Assumptions!B15 -> 8000 | F11: Operating expenses paid
C12: Wages expense | D12: =Assumptions!B16 -> 18000
C13: Utilities expense | D13: =Assumptions!B17 -> 3500
C14: Supplies & misc expense | D14: =Assumptions!B18 -> 2500
C15: Marketing expense | D15: =Assumptions!B19 -> 800
C16: Cash on hand | E16: =SUM(D11:D15) -> 32800 | F16: Opex settled in cash
C18: TOTALS | D18: =SUM(D4:D16) -> 379118.2 | E18: =SUM(E4:E16) -> 379118.2
C19: Check (Dr − Cr) | D19: =D18-E18 -> 0 | E19: =IF(D19=0,"BALANCED","OUT BY "&TEXT(D19,"#,##0")) -> BALANCED

Sheet Variance
A1: Variance Analysis — Actual vs Budget
A2: Budget cells (blue) are editable targets.
A4: Line | B4: Actual ฿ | C4: Budget ฿ | D4: Variance ฿ | E4: Var % | F4: Flag
A5: Total Revenue | B5: =IncomeStatement!B8 -> 246510 | C5: 235000 | D5: =B5-C5 -> 11510 | E5: =IFERROR(D5/C5,0) -> 0.048978723 | F5: =IF(D5>=0,"Favourable","Unfavourable") -> Favourable
A6: Total COGS | B6: =IncomeStatement!B12 -> 99808.2 | C6: 95000 | D6: =B6-C6 -> 4808.2 | E6: =IFERROR(D6/C6,0) -> 0.050612632 | F6: =IF(D6<=0,"Favourable","Unfavourable") -> Unfavourable
A7: Gross Profit | B7: =IncomeStatement!B13 -> 146701.8 | C7: =C5-C6 -> 140000 | D7: =B7-C7 -> 6701.8 | E7: =IFERROR(D7/C7,0) -> 0.04787 | F7: =IF(D7>=0,"Favourable","Unfavourable") -> Favourable
A8: Operating Expenses | B8: =IncomeStatement!B20 -> 32800 | C8: 34000 | D8: =B8-C8 -> -1200 | E8: =IFERROR(D8/C8,0) -> -0.035294118 | F8: =IF(D8<=0,"Favourable","Unfavourable") -> Favourable
A9: Net Profit | B9: =IncomeStatement!B21 -> 113901.8 | C9: =C7-C8 -> 106000 | D9: =B9-C9 -> 7901.8 | E9: =IFERROR(D9/C9,0) -> 0.074545283 | F9: =IF(D9>=0,"Favourable","Unfavourable") -> Favourable
A11: Favourable = better than target (more revenue/profit, or lower cost).
